ads4gpts_langchain/__init__.py
ads4gpts_langchain/toolkit.py
ads4gpts_langchain/tools.py
ads4gpts_langchain/utils.py
ads4gpts_langchain/tests/__init__.py
ads4gpts_langchain/tests/test_tools.py
build/lib/ads4gpts_langchain/__init__.py
build/lib/ads4gpts_langchain/toolkit.py
build/lib/ads4gpts_langchain/tools.py
build/lib/ads4gpts_langchain/utils.py
build/lib/ads4gpts_langchain/tests/__init__.py
build/lib/ads4gpts_langchain/tests/test_tools.py
build/lib/build/lib/ads4gpts_langchain/__init__.py
build/lib/build/lib/ads4gpts_langchain/toolkit.py
build/lib/build/lib/ads4gpts_langchain/tools.py
build/lib/build/lib/ads4gpts_langchain/utils.py
build/lib/build/lib/ads4gpts_langchain/tests/__init__.py
build/lib/build/lib/ads4gpts_langchain/tests/test_tools.py
build/lib/build/lib/build/lib/ads4gpts_langchain/__init__.py
build/lib/build/lib/build/lib/ads4gpts_langchain/toolkit.py
build/lib/build/lib/build/lib/ads4gpts_langchain/tools.py
build/lib/build/lib/build/lib/ads4gpts_langchain/utils.py
build/lib/build/lib/build/lib/ads4gpts_langchain/tests/__init__.py
build/lib/build/lib/build/lib/ads4gpts_langchain/tests/test_tools.py
build/lib/build/lib/build/lib/build/lib/ads4gpts_langchain/__init__.py
build/lib/build/lib/build/lib/build/lib/ads4gpts_langchain/toolkit.py
build/lib/build/lib/build/lib/build/lib/ads4gpts_langchain/tools.py
build/lib/build/lib/build/lib/build/lib/ads4gpts_langchain/utils.py
build/lib/build/lib/build/lib/build/lib/ads4gpts_langchain/tests/__init__.py
build/lib/build/lib/build/lib/build/lib/ads4gpts_langchain/tests/test_tools.py
build/lib/build/lib/build/lib/build/lib/build/lib/ads4gpts_langchain/__init__.py
build/lib/build/lib/build/lib/build/lib/build/lib/ads4gpts_langchain/toolkit.py
build/lib/build/lib/build/lib/build/lib/build/lib/ads4gpts_langchain/tools.py
build/lib/build/lib/build/lib/build/lib/build/lib/ads4gpts_langchain/utils.py
build/lib/build/lib/build/lib/build/lib/build/lib/ads4gpts_langchain/tests/__init__.py
ads4gpts_langchain-0.1.15.dist-info/LICENSE
ads4gpts_langchain-0.1.15.dist-info/METADATA
ads4gpts_langchain-0.1.15.dist-info/WHEEL
ads4gpts_langchain-0.1.15.dist-info/top_level.txt
ads4gpts_langchain-0.1.15.dist-info/RECORD
