Metadata-Version: 2.2
Name: ads4gpts-langchain
Version: 0.1.15
Summary: Ads for AI applications. Enabling the Freemium model for the AI era.
Home-page: https://www.ads4gpts.com/
Author: ADS4GPTs
Author-email: Ioannis Bakagiannis <contact@ads4gpts.com>
License:                     GNU AFFERO GENERAL PUBLIC LICENSE
Keywords: ads,GPT,LLM,freemium,AI
Classifier: Intended Audience :: Developers
Classifier: Programming Language :: Python :: 3.11
Classifier: Topic :: Software Development :: Libraries :: Python Modules
Requires-Python: >=3.11,<4.0
License-File: LICENSE
Dynamic: author
Dynamic: home-page
Dynamic: requires-python
